Church_rec_manager/__init__.py
Church_rec_manager/church_rec.py
Church_rec_manager/middleware/Baptism.py
Church_rec_manager/middleware/Confirmation.py
Church_rec_manager/middleware/__init__.py
Church_rec_manager/middleware/dbconnection.py
Church_rec_manager/middleware/death.py
Church_rec_manager/middleware/marriage.py
Church_rec_manager/middleware/storefile.py
Church_rec_manager/middleware/database_schema/Tables.py
Church_rec_manager/middleware/database_schema/__init__.py
Church_rec_manager/ui/App.py
Church_rec_manager/ui/BaptismTable.py
Church_rec_manager/ui/DeathTable.py
Church_rec_manager/ui/Left_Frame.py
Church_rec_manager/ui/MarriageTable.py
Church_rec_manager/ui/Navigation.py
Church_rec_manager/ui/Preview.py
Church_rec_manager/ui/__init__.py
Church_rec_manager/ui/RecordManagers/Baptism_.py
Church_rec_manager/ui/RecordManagers/Death_.py
Church_rec_manager/ui/RecordManagers/Marriage_.py
Church_rec_manager/ui/RecordManagers/__init__.py
Church_rec_manager/ui/components/Btn_Notify.py
Church_rec_manager/ui/components/Table.py
Church_rec_manager/ui/components/__init__.py
church_rec_manager-0.3.0.dist-info/LICENSE
church_rec_manager-0.3.0.dist-info/METADATA
church_rec_manager-0.3.0.dist-info/WHEEL
church_rec_manager-0.3.0.dist-info/entry_points.txt
church_rec_manager-0.3.0.dist-info/top_level.txt
church_rec_manager-0.3.0.dist-info/RECORD
